[
  {
    "name": "Junyi Chu",
    "affiliation": "Stanford University",
    "website": "https://cogtoolslab.github.io/people.html",
    "imageUrl": "/people/fanJE.jpg"
  },
  {
    "name": "Guy Davidson",
    "affiliation": "New York University",
    "website": "https://www.coalas-lab.com/elisakreiss",
    "imageUrl": "/people/kreissE.png"
  },
  {
    "name": "Arnav Verma",
    "affiliation": "Stanford University",
    "website": "https://www.lacepadilla.com/",
    "imageUrl": "/people/padillaL.jpg"
  },
  {
    "name": "Judy Fan",
    "affiliation": "Stanford University",
    "website": "https://cogtoolslab.github.io/people.html",
    "imageUrl": "/people/fanJE.jpg"
  }
]
